printerform/__init__.py
PrettyPrinterProject-0.1.dist-info/LICENSE.txt
PrettyPrinterProject-0.1.dist-info/METADATA
PrettyPrinterProject-0.1.dist-info/WHEEL
PrettyPrinterProject-0.1.dist-info/top_level.txt
PrettyPrinterProject-0.1.dist-info/RECORD
