Metadata-Version: 2.1
Name: PrettyPrinterProject
Version: 0.1
Summary: Pretty printing the dictionary data
Author: Kranthi_Sareddy
Author-email: sareddykranthi1997@gmail.com
Classifier: Programming Language :: Python :: 3
Classifier: License :: OSI Approved :: MIT License
Classifier: Operating System :: OS Independent
License-File: LICENSE.txt
